LICENSE.md
README.md
setup.py
buff163_unofficial_api/__init__.py
buff163_unofficial_api/buff163_unofficial_api.py
buff163_unofficial_api/cs_enums.py
buff163_unofficial_api/exceptions.py
buff163_unofficial_api/models.py
buff163_unofficial_api/rest_adapter.py
buff163_unofficial_api.egg-info/PKG-INFO
buff163_unofficial_api.egg-info/SOURCES.txt
buff163_unofficial_api.egg-info/dependency_links.txt
buff163_unofficial_api.egg-info/top_level.txt
tests/__init__.py
tests/test_buff163_api.py
tests/test_rest_adapter.py